undo_chat/__init__.py
undo_chat/chat.py
undo_chat/completer.py
undo_chat/history.py
undo_chat/main.py
undo_chat/message_util.py
undo_chat/printer.py
undo_chat/prompt.py
undo_chat-0.1.0.dist-info/LICENSE
undo_chat-0.1.0.dist-info/METADATA
undo_chat-0.1.0.dist-info/WHEEL
undo_chat-0.1.0.dist-info/entry_points.txt
undo_chat-0.1.0.dist-info/RECORD
